<?xml version="1.0" encoding="utf-8"?>
<!-- https://learn.microsoft.com/dotnet/fundamentals/package-validation/diagnostic-ids -->
<Suppressions xmlns:xsi="http://www.w3.org/2001/XMLSchema-instance" xmlns:xsd="http://www.w3.org/2001/XMLSchema">
  <Suppression>
    <DiagnosticId>CP0001</DiagnosticId>
    <Target>T:Microsoft.Extensions.VectorData.KeywordHybridSearchExtensions</Target>
    <Left>lib/net10.0/Microsoft.Extensions.VectorData.Abstractions.dll</Left>
    <Right>lib/net10.0/Microsoft.Extensions.VectorData.Abstractions.dll</Right>
    <IsBaselineSuppression>true</IsBaselineSuppression>
  </Suppression>
  <Suppression>
    <DiagnosticId>CP0001</DiagnosticId>
    <Target>T:Microsoft.Extensions.VectorData.VectorSearchExtensions</Target>
    <Left>lib/net10.0/Microsoft.Extensions.VectorData.Abstractions.dll</Left>
    <Right>lib/net10.0/Microsoft.Extensions.VectorData.Abstractions.dll</Right>
    <IsBaselineSuppression>true</IsBaselineSuppression>
  </Suppression>
  <Suppression>
    <DiagnosticId>CP0001</DiagnosticId>
    <Target>T:Microsoft.Extensions.VectorData.VectorSearchFilter</Target>
    <Left>lib/net10.0/Microsoft.Extensions.VectorData.Abstractions.dll</Left>
    <Right>lib/net10.0/Microsoft.Extensions.VectorData.Abstractions.dll</Right>
    <IsBaselineSuppression>true</IsBaselineSuppression>
  </Suppression>
  <Suppression>
    <DiagnosticId>CP0001</DiagnosticId>
    <Target>T:Microsoft.Extensions.VectorData.VectorStoreExtensions</Target>
    <Left>lib/net10.0/Microsoft.Extensions.VectorData.Abstractions.dll</Left>
    <Right>lib/net10.0/Microsoft.Extensions.VectorData.Abstractions.dll</Right>
    <IsBaselineSuppression>true</IsBaselineSuppression>
  </Suppression>
  <Suppression>
    <DiagnosticId>CP0001</DiagnosticId>
    <Target>T:Microsoft.Extensions.VectorData.KeywordHybridSearchExtensions</Target>
    <Left>lib/net462/Microsoft.Extensions.VectorData.Abstractions.dll</Left>
    <Right>lib/net462/Microsoft.Extensions.VectorData.Abstractions.dll</Right>
    <IsBaselineSuppression>true</IsBaselineSuppression>
  </Suppression>
  <Suppression>
    <DiagnosticId>CP0001</DiagnosticId>
    <Target>T:Microsoft.Extensions.VectorData.VectorSearchExtensions</Target>
    <Left>lib/net462/Microsoft.Extensions.VectorData.Abstractions.dll</Left>
    <Right>lib/net462/Microsoft.Extensions.VectorData.Abstractions.dll</Right>
    <IsBaselineSuppression>true</IsBaselineSuppression>
  </Suppression>
  <Suppression>
    <DiagnosticId>CP0001</DiagnosticId>
    <Target>T:Microsoft.Extensions.VectorData.VectorSearchFilter</Target>
    <Left>lib/net462/Microsoft.Extensions.VectorData.Abstractions.dll</Left>
    <Right>lib/net462/Microsoft.Extensions.VectorData.Abstractions.dll</Right>
    <IsBaselineSuppression>true</IsBaselineSuppression>
  </Suppression>
  <Suppression>
    <DiagnosticId>CP0001</DiagnosticId>
    <Target>T:Microsoft.Extensions.VectorData.VectorStoreExtensions</Target>
    <Left>lib/net462/Microsoft.Extensions.VectorData.Abstractions.dll</Left>
    <Right>lib/net462/Microsoft.Extensions.VectorData.Abstractions.dll</Right>
    <IsBaselineSuppression>true</IsBaselineSuppression>
  </Suppression>
  <Suppression>
    <DiagnosticId>CP0001</DiagnosticId>
    <Target>T:Microsoft.Extensions.VectorData.KeywordHybridSearchExtensions</Target>
    <Left>lib/net8.0/Microsoft.Extensions.VectorData.Abstractions.dll</Left>
    <Right>lib/net8.0/Microsoft.Extensions.VectorData.Abstractions.dll</Right>
    <IsBaselineSuppression>true</IsBaselineSuppression>
  </Suppression>
  <Suppression>
    <DiagnosticId>CP0001</DiagnosticId>
    <Target>T:Microsoft.Extensions.VectorData.VectorSearchExtensions</Target>
    <Left>lib/net8.0/Microsoft.Extensions.VectorData.Abstractions.dll</Left>
    <Right>lib/net8.0/Microsoft.Extensions.VectorData.Abstractions.dll</Right>
    <IsBaselineSuppression>true</IsBaselineSuppression>
  </Suppression>
  <Suppression>
    <DiagnosticId>CP0001</DiagnosticId>
    <Target>T:Microsoft.Extensions.VectorData.VectorSearchFilter</Target>
    <Left>lib/net8.0/Microsoft.Extensions.VectorData.Abstractions.dll</Left>
    <Right>lib/net8.0/Microsoft.Extensions.VectorData.Abstractions.dll</Right>
    <IsBaselineSuppression>true</IsBaselineSuppression>
  </Suppression>
  <Suppression>
    <DiagnosticId>CP0001</DiagnosticId>
    <Target>T:Microsoft.Extensions.VectorData.VectorStoreExtensions</Target>
    <Left>lib/net8.0/Microsoft.Extensions.VectorData.Abstractions.dll</Left>
    <Right>lib/net8.0/Microsoft.Extensions.VectorData.Abstractions.dll</Right>
    <IsBaselineSuppression>true</IsBaselineSuppression>
  </Suppression>
  <Suppression>
    <DiagnosticId>CP0001</DiagnosticId>
    <Target>T:Microsoft.Extensions.VectorData.KeywordHybridSearchExtensions</Target>
    <Left>lib/netstandard2.0/Microsoft.Extensions.VectorData.Abstractions.dll</Left>
    <Right>lib/netstandard2.0/Microsoft.Extensions.VectorData.Abstractions.dll</Right>
    <IsBaselineSuppression>true</IsBaselineSuppression>
  </Suppression>
  <Suppression>
    <DiagnosticId>CP0001</DiagnosticId>
    <Target>T:Microsoft.Extensions.VectorData.VectorSearchExtensions</Target>
    <Left>lib/netstandard2.0/Microsoft.Extensions.VectorData.Abstractions.dll</Left>
    <Right>lib/netstandard2.0/Microsoft.Extensions.VectorData.Abstractions.dll</Right>
    <IsBaselineSuppression>true</IsBaselineSuppression>
  </Suppression>
  <Suppression>
    <DiagnosticId>CP0001</DiagnosticId>
    <Target>T:Microsoft.Extensions.VectorData.VectorSearchFilter</Target>
    <Left>lib/netstandard2.0/Microsoft.Extensions.VectorData.Abstractions.dll</Left>
    <Right>lib/netstandard2.0/Microsoft.Extensions.VectorData.Abstractions.dll</Right>
    <IsBaselineSuppression>true</IsBaselineSuppression>
  </Suppression>
  <Suppression>
    <DiagnosticId>CP0001</DiagnosticId>
    <Target>T:Microsoft.Extensions.VectorData.VectorStoreExtensions</Target>
    <Left>lib/netstandard2.0/Microsoft.Extensions.VectorData.Abstractions.dll</Left>
    <Right>lib/netstandard2.0/Microsoft.Extensions.VectorData.Abstractions.dll</Right>
    <IsBaselineSuppression>true</IsBaselineSuppression>
  </Suppression>
  <Suppression>
    <DiagnosticId>CP0002</DiagnosticId>
    <Target>M:Microsoft.Extensions.VectorData.HybridSearchOptions`1.get_OldFilter</Target>
    <Left>lib/net10.0/Microsoft.Extensions.VectorData.Abstractions.dll</Left>
    <Right>lib/net10.0/Microsoft.Extensions.VectorData.Abstractions.dll</Right>
    <IsBaselineSuppression>true</IsBaselineSuppression>
  </Suppression>
  <Suppression>
    <DiagnosticId>CP0002</DiagnosticId>
    <Target>M:Microsoft.Extensions.VectorData.HybridSearchOptions`1.set_OldFilter(Microsoft.Extensions.VectorData.VectorSearchFilter)</Target>
    <Left>lib/net10.0/Microsoft.Extensions.VectorData.Abstractions.dll</Left>
    <Right>lib/net10.0/Microsoft.Extensions.VectorData.Abstractions.dll</Right>
    <IsBaselineSuppression>true</IsBaselineSuppression>
  </Suppression>
  <Suppression>
    <DiagnosticId>CP0002</DiagnosticId>
    <Target>M:Microsoft.Extensions.VectorData.ProviderServices.CollectionModelBuilder.ProcessRecordDefinition(Microsoft.Extensions.VectorData.VectorStoreCollectionDefinition,System.Type)</Target>
    <Left>lib/net10.0/Microsoft.Extensions.VectorData.Abstractions.dll</Left>
    <Right>lib/net10.0/Microsoft.Extensions.VectorData.Abstractions.dll</Right>
    <IsBaselineSuppression>true</IsBaselineSuppression>
  </Suppression>
  <Suppression>
    <DiagnosticId>CP0002</DiagnosticId>
    <Target>M:Microsoft.Extensions.VectorData.ProviderServices.CollectionModelBuilder.ProcessTypeProperties(System.Type,Microsoft.Extensions.VectorData.VectorStoreCollectionDefinition)</Target>
    <Left>lib/net10.0/Microsoft.Extensions.VectorData.Abstractions.dll</Left>
    <Right>lib/net10.0/Microsoft.Extensions.VectorData.Abstractions.dll</Right>
    <IsBaselineSuppression>true</IsBaselineSuppression>
  </Suppression>
  <Suppression>
    <DiagnosticId>CP0002</DiagnosticId>
    <Target>M:Microsoft.Extensions.VectorData.ProviderServices.Filter.FilterTranslatorBase.TryUnwrapSpanImplicitCast(System.Linq.Expressions.Expression,System.Linq.Expressions.Expression@)</Target>
    <Left>lib/net10.0/Microsoft.Extensions.VectorData.Abstractions.dll</Left>
    <Right>lib/net10.0/Microsoft.Extensions.VectorData.Abstractions.dll</Right>
    <IsBaselineSuppression>true</IsBaselineSuppression>
  </Suppression>
  <Suppression>
    <DiagnosticId>CP0002</DiagnosticId>
    <Target>M:Microsoft.Extensions.VectorData.ProviderServices.PropertyModel.get_TemporaryStorageName</Target>
    <Left>lib/net10.0/Microsoft.Extensions.VectorData.Abstractions.dll</Left>
    <Right>lib/net10.0/Microsoft.Extensions.VectorData.Abstractions.dll</Right>
    <IsBaselineSuppression>true</IsBaselineSuppression>
  </Suppression>
  <Suppression>
    <DiagnosticId>CP0002</DiagnosticId>
    <Target>M:Microsoft.Extensions.VectorData.ProviderServices.PropertyModel.set_TemporaryStorageName(System.String)</Target>
    <Left>lib/net10.0/Microsoft.Extensions.VectorData.Abstractions.dll</Left>
    <Right>lib/net10.0/Microsoft.Extensions.VectorData.Abstractions.dll</Right>
    <IsBaselineSuppression>true</IsBaselineSuppression>
  </Suppression>
  <Suppression>
    <DiagnosticId>CP0002</DiagnosticId>
    <Target>M:Microsoft.Extensions.VectorData.ProviderServices.VectorDataStrings.ConfiguredEmbeddingTypeIsUnsupportedByTheGenerator(Microsoft.Extensions.VectorData.ProviderServices.VectorPropertyModel,System.Type,System.String)</Target>
    <Left>lib/net10.0/Microsoft.Extensions.VectorData.Abstractions.dll</Left>
    <Right>lib/net10.0/Microsoft.Extensions.VectorData.Abstractions.dll</Right>
    <IsBaselineSuppression>true</IsBaselineSuppression>
  </Suppression>
  <Suppression>
    <DiagnosticId>CP0002</DiagnosticId>
    <Target>M:Microsoft.Extensions.VectorData.VectorSearchOptions`1.get_OldFilter</Target>
    <Left>lib/net10.0/Microsoft.Extensions.VectorData.Abstractions.dll</Left>
    <Right>lib/net10.0/Microsoft.Extensions.VectorData.Abstractions.dll</Right>
    <IsBaselineSuppression>true</IsBaselineSuppression>
  </Suppression>
  <Suppression>
    <DiagnosticId>CP0002</DiagnosticId>
    <Target>M:Microsoft.Extensions.VectorData.VectorSearchOptions`1.set_OldFilter(Microsoft.Extensions.VectorData.VectorSearchFilter)</Target>
    <Left>lib/net10.0/Microsoft.Extensions.VectorData.Abstractions.dll</Left>
    <Right>lib/net10.0/Microsoft.Extensions.VectorData.Abstractions.dll</Right>
    <IsBaselineSuppression>true</IsBaselineSuppression>
  </Suppression>
  <Suppression>
    <DiagnosticId>CP0002</DiagnosticId>
    <Target>M:Microsoft.Extensions.VectorData.VectorStoreKeyAttribute.get_IsAutoGenerated</Target>
    <Left>lib/net10.0/Microsoft.Extensions.VectorData.Abstractions.dll</Left>
    <Right>lib/net10.0/Microsoft.Extensions.VectorData.Abstractions.dll</Right>
    <IsBaselineSuppression>true</IsBaselineSuppression>
  </Suppression>
  <Suppression>
    <DiagnosticId>CP0002</DiagnosticId>
    <Target>M:Microsoft.Extensions.VectorData.HybridSearchOptions`1.get_OldFilter</Target>
    <Left>lib/net462/Microsoft.Extensions.VectorData.Abstractions.dll</Left>
    <Right>lib/net462/Microsoft.Extensions.VectorData.Abstractions.dll</Right>
    <IsBaselineSuppression>true</IsBaselineSuppression>
  </Suppression>
  <Suppression>
    <DiagnosticId>CP0002</DiagnosticId>
    <Target>M:Microsoft.Extensions.VectorData.HybridSearchOptions`1.set_OldFilter(Microsoft.Extensions.VectorData.VectorSearchFilter)</Target>
    <Left>lib/net462/Microsoft.Extensions.VectorData.Abstractions.dll</Left>
    <Right>lib/net462/Microsoft.Extensions.VectorData.Abstractions.dll</Right>
    <IsBaselineSuppression>true</IsBaselineSuppression>
  </Suppression>
  <Suppression>
    <DiagnosticId>CP0002</DiagnosticId>
    <Target>M:Microsoft.Extensions.VectorData.ProviderServices.CollectionModelBuilder.ProcessRecordDefinition(Microsoft.Extensions.VectorData.VectorStoreCollectionDefinition,System.Type)</Target>
    <Left>lib/net462/Microsoft.Extensions.VectorData.Abstractions.dll</Left>
    <Right>lib/net462/Microsoft.Extensions.VectorData.Abstractions.dll</Right>
    <IsBaselineSuppression>true</IsBaselineSuppression>
  </Suppression>
  <Suppression>
    <DiagnosticId>CP0002</DiagnosticId>
    <Target>M:Microsoft.Extensions.VectorData.ProviderServices.CollectionModelBuilder.ProcessTypeProperties(System.Type,Microsoft.Extensions.VectorData.VectorStoreCollectionDefinition)</Target>
    <Left>lib/net462/Microsoft.Extensions.VectorData.Abstractions.dll</Left>
    <Right>lib/net462/Microsoft.Extensions.VectorData.Abstractions.dll</Right>
    <IsBaselineSuppression>true</IsBaselineSuppression>
  </Suppression>
  <Suppression>
    <DiagnosticId>CP0002</DiagnosticId>
    <Target>M:Microsoft.Extensions.VectorData.ProviderServices.Filter.FilterTranslatorBase.TryUnwrapSpanImplicitCast(System.Linq.Expressions.Expression,System.Linq.Expressions.Expression@)</Target>
    <Left>lib/net462/Microsoft.Extensions.VectorData.Abstractions.dll</Left>
    <Right>lib/net462/Microsoft.Extensions.VectorData.Abstractions.dll</Right>
    <IsBaselineSuppression>true</IsBaselineSuppression>
  </Suppression>
  <Suppression>
    <DiagnosticId>CP0002</DiagnosticId>
    <Target>M:Microsoft.Extensions.VectorData.ProviderServices.PropertyModel.get_TemporaryStorageName</Target>
    <Left>lib/net462/Microsoft.Extensions.VectorData.Abstractions.dll</Left>
    <Right>lib/net462/Microsoft.Extensions.VectorData.Abstractions.dll</Right>
    <IsBaselineSuppression>true</IsBaselineSuppression>
  </Suppression>
  <Suppression>
    <DiagnosticId>CP0002</DiagnosticId>
    <Target>M:Microsoft.Extensions.VectorData.ProviderServices.PropertyModel.set_TemporaryStorageName(System.String)</Target>
    <Left>lib/net462/Microsoft.Extensions.VectorData.Abstractions.dll</Left>
    <Right>lib/net462/Microsoft.Extensions.VectorData.Abstractions.dll</Right>
    <IsBaselineSuppression>true</IsBaselineSuppression>
  </Suppression>
  <Suppression>
    <DiagnosticId>CP0002</DiagnosticId>
    <Target>M:Microsoft.Extensions.VectorData.ProviderServices.VectorDataStrings.ConfiguredEmbeddingTypeIsUnsupportedByTheGenerator(Microsoft.Extensions.VectorData.ProviderServices.VectorPropertyModel,System.Type,System.String)</Target>
    <Left>lib/net462/Microsoft.Extensions.VectorData.Abstractions.dll</Left>
    <Right>lib/net462/Microsoft.Extensions.VectorData.Abstractions.dll</Right>
    <IsBaselineSuppression>true</IsBaselineSuppression>
  </Suppression>
  <Suppression>
    <DiagnosticId>CP0002</DiagnosticId>
    <Target>M:Microsoft.Extensions.VectorData.VectorSearchOptions`1.get_OldFilter</Target>
    <Left>lib/net462/Microsoft.Extensions.VectorData.Abstractions.dll</Left>
    <Right>lib/net462/Microsoft.Extensions.VectorData.Abstractions.dll</Right>
    <IsBaselineSuppression>true</IsBaselineSuppression>
  </Suppression>
  <Suppression>
    <DiagnosticId>CP0002</DiagnosticId>
    <Target>M:Microsoft.Extensions.VectorData.VectorSearchOptions`1.set_OldFilter(Microsoft.Extensions.VectorData.VectorSearchFilter)</Target>
    <Left>lib/net462/Microsoft.Extensions.VectorData.Abstractions.dll</Left>
    <Right>lib/net462/Microsoft.Extensions.VectorData.Abstractions.dll</Right>
    <IsBaselineSuppression>true</IsBaselineSuppression>
  </Suppression>
  <Suppression>
    <DiagnosticId>CP0002</DiagnosticId>
    <Target>M:Microsoft.Extensions.VectorData.VectorStoreKeyAttribute.get_IsAutoGenerated</Target>
    <Left>lib/net462/Microsoft.Extensions.VectorData.Abstractions.dll</Left>
    <Right>lib/net462/Microsoft.Extensions.VectorData.Abstractions.dll</Right>
    <IsBaselineSuppression>true</IsBaselineSuppression>
  </Suppression>
  <Suppression>
    <DiagnosticId>CP0002</DiagnosticId>
    <Target>M:Microsoft.Extensions.VectorData.HybridSearchOptions`1.get_OldFilter</Target>
    <Left>lib/net8.0/Microsoft.Extensions.VectorData.Abstractions.dll</Left>
    <Right>lib/net8.0/Microsoft.Extensions.VectorData.Abstractions.dll</Right>
    <IsBaselineSuppression>true</IsBaselineSuppression>
  </Suppression>
  <Suppression>
    <DiagnosticId>CP0002</DiagnosticId>
    <Target>M:Microsoft.Extensions.VectorData.HybridSearchOptions`1.set_OldFilter(Microsoft.Extensions.VectorData.VectorSearchFilter)</Target>
    <Left>lib/net8.0/Microsoft.Extensions.VectorData.Abstractions.dll</Left>
    <Right>lib/net8.0/Microsoft.Extensions.VectorData.Abstractions.dll</Right>
    <IsBaselineSuppression>true</IsBaselineSuppression>
  </Suppression>
  <Suppression>
    <DiagnosticId>CP0002</DiagnosticId>
    <Target>M:Microsoft.Extensions.VectorData.ProviderServices.CollectionModelBuilder.ProcessRecordDefinition(Microsoft.Extensions.VectorData.VectorStoreCollectionDefinition,System.Type)</Target>
    <Left>lib/net8.0/Microsoft.Extensions.VectorData.Abstractions.dll</Left>
    <Right>lib/net8.0/Microsoft.Extensions.VectorData.Abstractions.dll</Right>
    <IsBaselineSuppression>true</IsBaselineSuppression>
  </Suppression>
  <Suppression>
    <DiagnosticId>CP0002</DiagnosticId>
    <Target>M:Microsoft.Extensions.VectorData.ProviderServices.CollectionModelBuilder.ProcessTypeProperties(System.Type,Microsoft.Extensions.VectorData.VectorStoreCollectionDefinition)</Target>
    <Left>lib/net8.0/Microsoft.Extensions.VectorData.Abstractions.dll</Left>
    <Right>lib/net8.0/Microsoft.Extensions.VectorData.Abstractions.dll</Right>
    <IsBaselineSuppression>true</IsBaselineSuppression>
  </Suppression>
  <Suppression>
    <DiagnosticId>CP0002</DiagnosticId>
    <Target>M:Microsoft.Extensions.VectorData.ProviderServices.Filter.FilterTranslatorBase.TryUnwrapSpanImplicitCast(System.Linq.Expressions.Expression,System.Linq.Expressions.Expression@)</Target>
    <Left>lib/net8.0/Microsoft.Extensions.VectorData.Abstractions.dll</Left>
    <Right>lib/net8.0/Microsoft.Extensions.VectorData.Abstractions.dll</Right>
    <IsBaselineSuppression>true</IsBaselineSuppression>
  </Suppression>
  <Suppression>
    <DiagnosticId>CP0002</DiagnosticId>
    <Target>M:Microsoft.Extensions.VectorData.ProviderServices.PropertyModel.get_TemporaryStorageName</Target>
    <Left>lib/net8.0/Microsoft.Extensions.VectorData.Abstractions.dll</Left>
    <Right>lib/net8.0/Microsoft.Extensions.VectorData.Abstractions.dll</Right>
    <IsBaselineSuppression>true</IsBaselineSuppression>
  </Suppression>
  <Suppression>
    <DiagnosticId>CP0002</DiagnosticId>
    <Target>M:Microsoft.Extensions.VectorData.ProviderServices.PropertyModel.set_TemporaryStorageName(System.String)</Target>
    <Left>lib/net8.0/Microsoft.Extensions.VectorData.Abstractions.dll</Left>
    <Right>lib/net8.0/Microsoft.Extensions.VectorData.Abstractions.dll</Right>
    <IsBaselineSuppression>true</IsBaselineSuppression>
  </Suppression>
  <Suppression>
    <DiagnosticId>CP0002</DiagnosticId>
    <Target>M:Microsoft.Extensions.VectorData.ProviderServices.VectorDataStrings.ConfiguredEmbeddingTypeIsUnsupportedByTheGenerator(Microsoft.Extensions.VectorData.ProviderServices.VectorPropertyModel,System.Type,System.String)</Target>
    <Left>lib/net8.0/Microsoft.Extensions.VectorData.Abstractions.dll</Left>
    <Right>lib/net8.0/Microsoft.Extensions.VectorData.Abstractions.dll</Right>
    <IsBaselineSuppression>true</IsBaselineSuppression>
  </Suppression>
  <Suppression>
    <DiagnosticId>CP0002</DiagnosticId>
    <Target>M:Microsoft.Extensions.VectorData.VectorSearchOptions`1.get_OldFilter</Target>
    <Left>lib/net8.0/Microsoft.Extensions.VectorData.Abstractions.dll</Left>
    <Right>lib/net8.0/Microsoft.Extensions.VectorData.Abstractions.dll</Right>
    <IsBaselineSuppression>true</IsBaselineSuppression>
  </Suppression>
  <Suppression>
    <DiagnosticId>CP0002</DiagnosticId>
    <Target>M:Microsoft.Extensions.VectorData.VectorSearchOptions`1.set_OldFilter(Microsoft.Extensions.VectorData.VectorSearchFilter)</Target>
    <Left>lib/net8.0/Microsoft.Extensions.VectorData.Abstractions.dll</Left>
    <Right>lib/net8.0/Microsoft.Extensions.VectorData.Abstractions.dll</Right>
    <IsBaselineSuppression>true</IsBaselineSuppression>
  </Suppression>
  <Suppression>
    <DiagnosticId>CP0002</DiagnosticId>
    <Target>M:Microsoft.Extensions.VectorData.VectorStoreKeyAttribute.get_IsAutoGenerated</Target>
    <Left>lib/net8.0/Microsoft.Extensions.VectorData.Abstractions.dll</Left>
    <Right>lib/net8.0/Microsoft.Extensions.VectorData.Abstractions.dll</Right>
    <IsBaselineSuppression>true</IsBaselineSuppression>
  </Suppression>
  <Suppression>
    <DiagnosticId>CP0002</DiagnosticId>
    <Target>M:Microsoft.Extensions.VectorData.HybridSearchOptions`1.get_OldFilter</Target>
    <Left>lib/netstandard2.0/Microsoft.Extensions.VectorData.Abstractions.dll</Left>
    <Right>lib/netstandard2.0/Microsoft.Extensions.VectorData.Abstractions.dll</Right>
    <IsBaselineSuppression>true</IsBaselineSuppression>
  </Suppression>
  <Suppression>
    <DiagnosticId>CP0002</DiagnosticId>
    <Target>M:Microsoft.Extensions.VectorData.HybridSearchOptions`1.set_OldFilter(Microsoft.Extensions.VectorData.VectorSearchFilter)</Target>
    <Left>lib/netstandard2.0/Microsoft.Extensions.VectorData.Abstractions.dll</Left>
    <Right>lib/netstandard2.0/Microsoft.Extensions.VectorData.Abstractions.dll</Right>
    <IsBaselineSuppression>true</IsBaselineSuppression>
  </Suppression>
  <Suppression>
    <DiagnosticId>CP0002</DiagnosticId>
    <Target>M:Microsoft.Extensions.VectorData.ProviderServices.CollectionModelBuilder.ProcessRecordDefinition(Microsoft.Extensions.VectorData.VectorStoreCollectionDefinition,System.Type)</Target>
    <Left>lib/netstandard2.0/Microsoft.Extensions.VectorData.Abstractions.dll</Left>
    <Right>lib/netstandard2.0/Microsoft.Extensions.VectorData.Abstractions.dll</Right>
    <IsBaselineSuppression>true</IsBaselineSuppression>
  </Suppression>
  <Suppression>
    <DiagnosticId>CP0002</DiagnosticId>
    <Target>M:Microsoft.Extensions.VectorData.ProviderServices.CollectionModelBuilder.ProcessTypeProperties(System.Type,Microsoft.Extensions.VectorData.VectorStoreCollectionDefinition)</Target>
    <Left>lib/netstandard2.0/Microsoft.Extensions.VectorData.Abstractions.dll</Left>
    <Right>lib/netstandard2.0/Microsoft.Extensions.VectorData.Abstractions.dll</Right>
    <IsBaselineSuppression>true</IsBaselineSuppression>
  </Suppression>
  <Suppression>
    <DiagnosticId>CP0002</DiagnosticId>
    <Target>M:Microsoft.Extensions.VectorData.ProviderServices.Filter.FilterTranslatorBase.TryUnwrapSpanImplicitCast(System.Linq.Expressions.Expression,System.Linq.Expressions.Expression@)</Target>
    <Left>lib/netstandard2.0/Microsoft.Extensions.VectorData.Abstractions.dll</Left>
    <Right>lib/netstandard2.0/Microsoft.Extensions.VectorData.Abstractions.dll</Right>
    <IsBaselineSuppression>true</IsBaselineSuppression>
  </Suppression>
  <Suppression>
    <DiagnosticId>CP0002</DiagnosticId>
    <Target>M:Microsoft.Extensions.VectorData.ProviderServices.PropertyModel.get_TemporaryStorageName</Target>
    <Left>lib/netstandard2.0/Microsoft.Extensions.VectorData.Abstractions.dll</Left>
    <Right>lib/netstandard2.0/Microsoft.Extensions.VectorData.Abstractions.dll</Right>
    <IsBaselineSuppression>true</IsBaselineSuppression>
  </Suppression>
  <Suppression>
    <DiagnosticId>CP0002</DiagnosticId>
    <Target>M:Microsoft.Extensions.VectorData.ProviderServices.PropertyModel.set_TemporaryStorageName(System.String)</Target>
    <Left>lib/netstandard2.0/Microsoft.Extensions.VectorData.Abstractions.dll</Left>
    <Right>lib/netstandard2.0/Microsoft.Extensions.VectorData.Abstractions.dll</Right>
    <IsBaselineSuppression>true</IsBaselineSuppression>
  </Suppression>
  <Suppression>
    <DiagnosticId>CP0002</DiagnosticId>
    <Target>M:Microsoft.Extensions.VectorData.ProviderServices.VectorDataStrings.ConfiguredEmbeddingTypeIsUnsupportedByTheGenerator(Microsoft.Extensions.VectorData.ProviderServices.VectorPropertyModel,System.Type,System.String)</Target>
    <Left>lib/netstandard2.0/Microsoft.Extensions.VectorData.Abstractions.dll</Left>
    <Right>lib/netstandard2.0/Microsoft.Extensions.VectorData.Abstractions.dll</Right>
    <IsBaselineSuppression>true</IsBaselineSuppression>
  </Suppression>
  <Suppression>
    <DiagnosticId>CP0002</DiagnosticId>
    <Target>M:Microsoft.Extensions.VectorData.VectorSearchOptions`1.get_OldFilter</Target>
    <Left>lib/netstandard2.0/Microsoft.Extensions.VectorData.Abstractions.dll</Left>
    <Right>lib/netstandard2.0/Microsoft.Extensions.VectorData.Abstractions.dll</Right>
    <IsBaselineSuppression>true</IsBaselineSuppression>
  </Suppression>
  <Suppression>
    <DiagnosticId>CP0002</DiagnosticId>
    <Target>M:Microsoft.Extensions.VectorData.VectorSearchOptions`1.set_OldFilter(Microsoft.Extensions.VectorData.VectorSearchFilter)</Target>
    <Left>lib/netstandard2.0/Microsoft.Extensions.VectorData.Abstractions.dll</Left>
    <Right>lib/netstandard2.0/Microsoft.Extensions.VectorData.Abstractions.dll</Right>
    <IsBaselineSuppression>true</IsBaselineSuppression>
  </Suppression>
  <Suppression>
    <DiagnosticId>CP0002</DiagnosticId>
    <Target>M:Microsoft.Extensions.VectorData.VectorStoreKeyAttribute.get_IsAutoGenerated</Target>
    <Left>lib/netstandard2.0/Microsoft.Extensions.VectorData.Abstractions.dll</Left>
    <Right>lib/netstandard2.0/Microsoft.Extensions.VectorData.Abstractions.dll</Right>
    <IsBaselineSuppression>true</IsBaselineSuppression>
  </Suppression>
  <Suppression>
    <DiagnosticId>CP0012</DiagnosticId>
    <Target>M:Microsoft.Extensions.VectorData.ProviderServices.PropertyModel.GetValue``1(System.Object)</Target>
    <Left>lib/net10.0/Microsoft.Extensions.VectorData.Abstractions.dll</Left>
    <Right>lib/net10.0/Microsoft.Extensions.VectorData.Abstractions.dll</Right>
    <IsBaselineSuppression>true</IsBaselineSuppression>
  </Suppression>
  <Suppression>
    <DiagnosticId>CP0012</DiagnosticId>
    <Target>M:Microsoft.Extensions.VectorData.ProviderServices.PropertyModel.GetValueAsObject(System.Object)</Target>
    <Left>lib/net10.0/Microsoft.Extensions.VectorData.Abstractions.dll</Left>
    <Right>lib/net10.0/Microsoft.Extensions.VectorData.Abstractions.dll</Right>
    <IsBaselineSuppression>true</IsBaselineSuppression>
  </Suppression>
  <Suppression>
    <DiagnosticId>CP0012</DiagnosticId>
    <Target>M:Microsoft.Extensions.VectorData.ProviderServices.PropertyModel.SetValue``1(System.Object,``0)</Target>
    <Left>lib/net10.0/Microsoft.Extensions.VectorData.Abstractions.dll</Left>
    <Right>lib/net10.0/Microsoft.Extensions.VectorData.Abstractions.dll</Right>
    <IsBaselineSuppression>true</IsBaselineSuppression>
  </Suppression>
  <Suppression>
    <DiagnosticId>CP0012</DiagnosticId>
    <Target>M:Microsoft.Extensions.VectorData.ProviderServices.PropertyModel.SetValueAsObject(System.Object,System.Object)</Target>
    <Left>lib/net10.0/Microsoft.Extensions.VectorData.Abstractions.dll</Left>
    <Right>lib/net10.0/Microsoft.Extensions.VectorData.Abstractions.dll</Right>
    <IsBaselineSuppression>true</IsBaselineSuppression>
  </Suppression>
  <Suppression>
    <DiagnosticId>CP0012</DiagnosticId>
    <Target>M:Microsoft.Extensions.VectorData.ProviderServices.PropertyModel.GetValue``1(System.Object)</Target>
    <Left>lib/net462/Microsoft.Extensions.VectorData.Abstractions.dll</Left>
    <Right>lib/net462/Microsoft.Extensions.VectorData.Abstractions.dll</Right>
    <IsBaselineSuppression>true</IsBaselineSuppression>
  </Suppression>
  <Suppression>
    <DiagnosticId>CP0012</DiagnosticId>
    <Target>M:Microsoft.Extensions.VectorData.ProviderServices.PropertyModel.GetValueAsObject(System.Object)</Target>
    <Left>lib/net462/Microsoft.Extensions.VectorData.Abstractions.dll</Left>
    <Right>lib/net462/Microsoft.Extensions.VectorData.Abstractions.dll</Right>
    <IsBaselineSuppression>true</IsBaselineSuppression>
  </Suppression>
  <Suppression>
    <DiagnosticId>CP0012</DiagnosticId>
    <Target>M:Microsoft.Extensions.VectorData.ProviderServices.PropertyModel.SetValue``1(System.Object,``0)</Target>
    <Left>lib/net462/Microsoft.Extensions.VectorData.Abstractions.dll</Left>
    <Right>lib/net462/Microsoft.Extensions.VectorData.Abstractions.dll</Right>
    <IsBaselineSuppression>true</IsBaselineSuppression>
  </Suppression>
  <Suppression>
    <DiagnosticId>CP0012</DiagnosticId>
    <Target>M:Microsoft.Extensions.VectorData.ProviderServices.PropertyModel.SetValueAsObject(System.Object,System.Object)</Target>
    <Left>lib/net462/Microsoft.Extensions.VectorData.Abstractions.dll</Left>
    <Right>lib/net462/Microsoft.Extensions.VectorData.Abstractions.dll</Right>
    <IsBaselineSuppression>true</IsBaselineSuppression>
  </Suppression>
  <Suppression>
    <DiagnosticId>CP0012</DiagnosticId>
    <Target>M:Microsoft.Extensions.VectorData.ProviderServices.PropertyModel.GetValue``1(System.Object)</Target>
    <Left>lib/net8.0/Microsoft.Extensions.VectorData.Abstractions.dll</Left>
    <Right>lib/net8.0/Microsoft.Extensions.VectorData.Abstractions.dll</Right>
    <IsBaselineSuppression>true</IsBaselineSuppression>
  </Suppression>
  <Suppression>
    <DiagnosticId>CP0012</DiagnosticId>
    <Target>M:Microsoft.Extensions.VectorData.ProviderServices.PropertyModel.GetValueAsObject(System.Object)</Target>
    <Left>lib/net8.0/Microsoft.Extensions.VectorData.Abstractions.dll</Left>
    <Right>lib/net8.0/Microsoft.Extensions.VectorData.Abstractions.dll</Right>
    <IsBaselineSuppression>true</IsBaselineSuppression>
  </Suppression>
  <Suppression>
    <DiagnosticId>CP0012</DiagnosticId>
    <Target>M:Microsoft.Extensions.VectorData.ProviderServices.PropertyModel.SetValue``1(System.Object,``0)</Target>
    <Left>lib/net8.0/Microsoft.Extensions.VectorData.Abstractions.dll</Left>
    <Right>lib/net8.0/Microsoft.Extensions.VectorData.Abstractions.dll</Right>
    <IsBaselineSuppression>true</IsBaselineSuppression>
  </Suppression>
  <Suppression>
    <DiagnosticId>CP0012</DiagnosticId>
    <Target>M:Microsoft.Extensions.VectorData.ProviderServices.PropertyModel.SetValueAsObject(System.Object,System.Object)</Target>
    <Left>lib/net8.0/Microsoft.Extensions.VectorData.Abstractions.dll</Left>
    <Right>lib/net8.0/Microsoft.Extensions.VectorData.Abstractions.dll</Right>
    <IsBaselineSuppression>true</IsBaselineSuppression>
  </Suppression>
  <Suppression>
    <DiagnosticId>CP0012</DiagnosticId>
    <Target>M:Microsoft.Extensions.VectorData.ProviderServices.PropertyModel.GetValue``1(System.Object)</Target>
    <Left>lib/netstandard2.0/Microsoft.Extensions.VectorData.Abstractions.dll</Left>
    <Right>lib/netstandard2.0/Microsoft.Extensions.VectorData.Abstractions.dll</Right>
    <IsBaselineSuppression>true</IsBaselineSuppression>
  </Suppression>
  <Suppression>
    <DiagnosticId>CP0012</DiagnosticId>
    <Target>M:Microsoft.Extensions.VectorData.ProviderServices.PropertyModel.GetValueAsObject(System.Object)</Target>
    <Left>lib/netstandard2.0/Microsoft.Extensions.VectorData.Abstractions.dll</Left>
    <Right>lib/netstandard2.0/Microsoft.Extensions.VectorData.Abstractions.dll</Right>
    <IsBaselineSuppression>true</IsBaselineSuppression>
  </Suppression>
  <Suppression>
    <DiagnosticId>CP0012</DiagnosticId>
    <Target>M:Microsoft.Extensions.VectorData.ProviderServices.PropertyModel.SetValue``1(System.Object,``0)</Target>
    <Left>lib/netstandard2.0/Microsoft.Extensions.VectorData.Abstractions.dll</Left>
    <Right>lib/netstandard2.0/Microsoft.Extensions.VectorData.Abstractions.dll</Right>
    <IsBaselineSuppression>true</IsBaselineSuppression>
  </Suppression>
  <Suppression>
    <DiagnosticId>CP0012</DiagnosticId>
    <Target>M:Microsoft.Extensions.VectorData.ProviderServices.PropertyModel.SetValueAsObject(System.Object,System.Object)</Target>
    <Left>lib/netstandard2.0/Microsoft.Extensions.VectorData.Abstractions.dll</Left>
    <Right>lib/netstandard2.0/Microsoft.Extensions.VectorData.Abstractions.dll</Right>
    <IsBaselineSuppression>true</IsBaselineSuppression>
  </Suppression>
  <Suppression>
    <DiagnosticId>CP0021</DiagnosticId>
    <Target>T:Microsoft.Extensions.VectorData.IKeywordHybridSearchable`1``0:class</Target>
    <Left>lib/net10.0/Microsoft.Extensions.VectorData.Abstractions.dll</Left>
    <Right>lib/net10.0/Microsoft.Extensions.VectorData.Abstractions.dll</Right>
    <IsBaselineSuppression>true</IsBaselineSuppression>
  </Suppression>
  <Suppression>
    <DiagnosticId>CP0021</DiagnosticId>
    <Target>T:Microsoft.Extensions.VectorData.IVectorSearchable`1``0:class</Target>
    <Left>lib/net10.0/Microsoft.Extensions.VectorData.Abstractions.dll</Left>
    <Right>lib/net10.0/Microsoft.Extensions.VectorData.Abstractions.dll</Right>
    <IsBaselineSuppression>true</IsBaselineSuppression>
  </Suppression>
  <Suppression>
    <DiagnosticId>CP0021</DiagnosticId>
    <Target>T:Microsoft.Extensions.VectorData.VectorSearchResult`1``0:class</Target>
    <Left>lib/net10.0/Microsoft.Extensions.VectorData.Abstractions.dll</Left>
    <Right>lib/net10.0/Microsoft.Extensions.VectorData.Abstractions.dll</Right>
    <IsBaselineSuppression>true</IsBaselineSuppression>
  </Suppression>
  <Suppression>
    <DiagnosticId>CP0021</DiagnosticId>
    <Target>T:Microsoft.Extensions.VectorData.IKeywordHybridSearchable`1``0:class</Target>
    <Left>lib/net462/Microsoft.Extensions.VectorData.Abstractions.dll</Left>
    <Right>lib/net462/Microsoft.Extensions.VectorData.Abstractions.dll</Right>
    <IsBaselineSuppression>true</IsBaselineSuppression>
  </Suppression>
  <Suppression>
    <DiagnosticId>CP0021</DiagnosticId>
    <Target>T:Microsoft.Extensions.VectorData.IVectorSearchable`1``0:class</Target>
    <Left>lib/net462/Microsoft.Extensions.VectorData.Abstractions.dll</Left>
    <Right>lib/net462/Microsoft.Extensions.VectorData.Abstractions.dll</Right>
    <IsBaselineSuppression>true</IsBaselineSuppression>
  </Suppression>
  <Suppression>
    <DiagnosticId>CP0021</DiagnosticId>
    <Target>T:Microsoft.Extensions.VectorData.VectorSearchResult`1``0:class</Target>
    <Left>lib/net462/Microsoft.Extensions.VectorData.Abstractions.dll</Left>
    <Right>lib/net462/Microsoft.Extensions.VectorData.Abstractions.dll</Right>
    <IsBaselineSuppression>true</IsBaselineSuppression>
  </Suppression>
  <Suppression>
    <DiagnosticId>CP0021</DiagnosticId>
    <Target>T:Microsoft.Extensions.VectorData.IKeywordHybridSearchable`1``0:class</Target>
    <Left>lib/net8.0/Microsoft.Extensions.VectorData.Abstractions.dll</Left>
    <Right>lib/net8.0/Microsoft.Extensions.VectorData.Abstractions.dll</Right>
    <IsBaselineSuppression>true</IsBaselineSuppression>
  </Suppression>
  <Suppression>
    <DiagnosticId>CP0021</DiagnosticId>
    <Target>T:Microsoft.Extensions.VectorData.IVectorSearchable`1``0:class</Target>
    <Left>lib/net8.0/Microsoft.Extensions.VectorData.Abstractions.dll</Left>
    <Right>lib/net8.0/Microsoft.Extensions.VectorData.Abstractions.dll</Right>
    <IsBaselineSuppression>true</IsBaselineSuppression>
  </Suppression>
  <Suppression>
    <DiagnosticId>CP0021</DiagnosticId>
    <Target>T:Microsoft.Extensions.VectorData.VectorSearchResult`1``0:class</Target>
    <Left>lib/net8.0/Microsoft.Extensions.VectorData.Abstractions.dll</Left>
    <Right>lib/net8.0/Microsoft.Extensions.VectorData.Abstractions.dll</Right>
    <IsBaselineSuppression>true</IsBaselineSuppression>
  </Suppression>
  <Suppression>
    <DiagnosticId>CP0021</DiagnosticId>
    <Target>T:Microsoft.Extensions.VectorData.IKeywordHybridSearchable`1``0:class</Target>
    <Left>lib/netstandard2.0/Microsoft.Extensions.VectorData.Abstractions.dll</Left>
    <Right>lib/netstandard2.0/Microsoft.Extensions.VectorData.Abstractions.dll</Right>
    <IsBaselineSuppression>true</IsBaselineSuppression>
  </Suppression>
  <Suppression>
    <DiagnosticId>CP0021</DiagnosticId>
    <Target>T:Microsoft.Extensions.VectorData.IVectorSearchable`1``0:class</Target>
    <Left>lib/netstandard2.0/Microsoft.Extensions.VectorData.Abstractions.dll</Left>
    <Right>lib/netstandard2.0/Microsoft.Extensions.VectorData.Abstractions.dll</Right>
    <IsBaselineSuppression>true</IsBaselineSuppression>
  </Suppression>
  <Suppression>
    <DiagnosticId>CP0021</DiagnosticId>
    <Target>T:Microsoft.Extensions.VectorData.VectorSearchResult`1``0:class</Target>
    <Left>lib/netstandard2.0/Microsoft.Extensions.VectorData.Abstractions.dll</Left>
    <Right>lib/netstandard2.0/Microsoft.Extensions.VectorData.Abstractions.dll</Right>
    <IsBaselineSuppression>true</IsBaselineSuppression>
  </Suppression>
</Suppressions>